[
    {
        "AvatarItemDesc": "d0a9262f-5504-46a7-bb10-7507503db58e,95e4cc30-cb68-473d-a395-feadf5b51512,0440f08f-ef1d-49d8-942b-523056e8bb45,0c496f32-0011-4c4d-9778-59446f70c032",
        "AvatarItemType": 0,
        "PlatformMask": -1,
        "FriendlyName": "Rec Room T-Shirt (Crew Neck, Orange)",
        "Tooltip": "",
        "Rarity": 0,
        "TagList": null,
        "AvatarItemId": 565,
        "IsBaseAvatarItem": false,
        "CreatedAt": "2017-11-16T22:47:23.843Z",
        "ThumbnailImage": "b1k80npgw88paq57cw285zhgv.png"
    },
    {
        "AvatarItemDesc":"193a3bf9-abc0-4d78-8d63-92046908b1c5,,,",
        "AvatarItemType":0,
        "PlatformMask":-1,
        "FriendlyName":"Emo Hair",
        "Tooltip":null,
        "Rarity":0,
        "TagList":null,
        "AvatarItemId":991,
        "IsBaseAvatarItem":false,
        "CreatedAt":"2019-02-26T18:16:06.46Z",
        "ThumbnailImage":"60usmea9f77xjypmnvoptbc9g.png"
    },
    {
        "AvatarItemDesc":"79b90274-6eec-4664-acfb-4a123334661e,,,",
        "AvatarItemType":0,
        "PlatformMask":-1,
        "FriendlyName":"Pig Tails Hair",
        "Tooltip":null,
        "Rarity":0,
        "TagList":null,
        "AvatarItemId":997,
        "IsBaseAvatarItem":false,
        "CreatedAt":"2019-02-26T18:16:17.347Z",
        "ThumbnailImage":"9gvfh0l74sodnh53dk03ioc7k.png"
    }
    
]
